ament_cppcheck/__init__.py
ament_cppcheck/main.py
ros_ament_cppcheck-0.19.2.data/data/share/ament_cppcheck/package.xml
ros_ament_cppcheck-0.19.2.data/data/share/ament_index/resource_index/packages/ament_cppcheck
ros_ament_cppcheck-0.19.2.dist-info/METADATA
ros_ament_cppcheck-0.19.2.dist-info/WHEEL
ros_ament_cppcheck-0.19.2.dist-info/entry_points.txt
ros_ament_cppcheck-0.19.2.dist-info/top_level.txt
ros_ament_cppcheck-0.19.2.dist-info/zip-safe
ros_ament_cppcheck-0.19.2.dist-info/RECORD
