Metadata-Version: 2.4
Name: ros-ament-cppcheck
Version: 0.19.2
Summary: Static code analysis on C/C++ code using Cppcheck.
Home-page: https://github.com/ament/ament_lint
Download-URL: https://github.com/ament/ament_lint/releases
Author: Dirk Thomas
Author-email: dthomas@osrfoundation.org
Maintainer: Michael Jeronimo
Maintainer-email: michael.jeronimo@openrobotics.org
License: Apache License, Version 2.0
Keywords: ROS
Classifier: Intended Audience :: Developers
Classifier: License :: OSI Approved :: Apache Software License
Classifier: Programming Language :: Python
Classifier: Topic :: Software Development
Requires-Dist: setuptools
Dynamic: author
Dynamic: author-email
Dynamic: classifier
Dynamic: description
Dynamic: download-url
Dynamic: home-page
Dynamic: keywords
Dynamic: license
Dynamic: maintainer
Dynamic: maintainer-email
Dynamic: requires-dist
Dynamic: summary
